switch/__init__.py
switch/switch.py
simple_switch-0.2.0.dist-info/LICENSE
simple_switch-0.2.0.dist-info/METADATA
simple_switch-0.2.0.dist-info/WHEEL
simple_switch-0.2.0.dist-info/top_level.txt
simple_switch-0.2.0.dist-info/RECORD
