Metadata-Version: 2.1
Name: simple-switch
Version: 0.2.0
Summary: A simple and flexible switch statement implementation for Python.
Home-page: https://github.com/TheDataDave/switch
Author: David Flanders
Author-email: thedatadave@gmail.com
Keywords: python,conditional,logic,switch,case,if-else,if,else
Classifier: Programming Language :: Python :: 3
Classifier: License :: OSI Approved :: MIT License
Classifier: Topic :: Software Development :: Libraries :: Python Modules
Classifier: Operating System :: OS Independent
License-File: LICENSE
